auth/__init__.py
auth/config/__init__.py
auth/dependency/__init__.py
auth/dependency/authorize.py
auth/dependency/kms_decrypt.py
auth/schemas/__init__.py
auth/schemas/bearer.py
auth/schemas/claims.py
auth/schemas/context.py
auth/schemas/encryption.py
auth/service/aes.py
auth/service/aws/__init__.py
auth/service/aws/client.py
auth/service/aws/kms/__init__.py
auth/service/aws/kms/schemas/__init__.py
auth/service/fernet.py
auth/service/jwe.py
auth/service/jwt.py
auth/service/token/__init__.py
auth/service/token/main.py
com_terra_auth-0.1.2.dist-info/licenses/LICENSE
com_terra_auth-0.1.2.dist-info/METADATA
com_terra_auth-0.1.2.dist-info/WHEEL
com_terra_auth-0.1.2.dist-info/RECORD
