Metadata-Version: 2.4
Name: com-terra-auth
Version: 0.1.2
Summary: Reusable authentication utility
License: MIT
License-File: LICENSE
Author: Telephone.com
Requires-Python: >=3.12,<4.0
Classifier: License :: OSI Approved :: MIT License
Classifier: Programming Language :: Python :: 3
Classifier: Programming Language :: Python :: 3.12
Classifier: Programming Language :: Python :: 3.13
Classifier: Programming Language :: Python :: 3.14
Requires-Dist: boto3 (>=1.40.18,<2.0.0)
Requires-Dist: cryptography (>=45.0,<46.0)
Requires-Dist: fastapi (>=0.111.0,<=0.116.1)
Requires-Dist: pydantic (>=2.11.7,<3.0.0)
Requires-Dist: python-jose (>=3.5.0,<4.0.0)
